ask_sdk_runtime/__init__.py
ask_sdk_runtime/__version__.py
ask_sdk_runtime/dispatch.py
ask_sdk_runtime/exceptions.py
ask_sdk_runtime/py.typed
ask_sdk_runtime/skill.py
ask_sdk_runtime/skill_builder.py
ask_sdk_runtime/utils.py
ask_sdk_runtime/dispatch_components/__init__.py
ask_sdk_runtime/dispatch_components/exception_components.py
ask_sdk_runtime/dispatch_components/py.typed
ask_sdk_runtime/dispatch_components/request_components.py
ask_sdk_runtime/view_resolvers/__init__.py
ask_sdk_runtime/view_resolvers/abstract_template_cache.py
ask_sdk_runtime/view_resolvers/abstract_template_enumerator.py
ask_sdk_runtime/view_resolvers/abstract_template_factory.py
ask_sdk_runtime/view_resolvers/abstract_template_loader.py
ask_sdk_runtime/view_resolvers/abstract_template_renderer.py
ask_sdk_runtime/view_resolvers/py.typed
ask_sdk_runtime-1.19.0.dist-info/METADATA
ask_sdk_runtime-1.19.0.dist-info/WHEEL
ask_sdk_runtime-1.19.0.dist-info/top_level.txt
ask_sdk_runtime-1.19.0.dist-info/RECORD
