Metadata-Version: 1.2
Name: ask-sdk-runtime
Version: 1.19.0
Summary: The ASK SDK Runtime package provides runtime componentsthat act as fundamental implementation layer for ASK SDKpackages
Home-page: https://github.com/alexa/alexa-skills-kit-sdk-for-python
Author: Alexa Skills Kit
Author-email: ask-sdk-dynamic@amazon.com
License: Apache 2.0
Keywords: ASK SDK Runtime,Alexa Skills Kit,Alexa,Runtime
Platform: UNKNOWN
Classifier: Development Status :: 5 - Production/Stable
Classifier: Intended Audience :: Developers
Classifier: Natural Language :: English
Classifier: License :: OSI Approved :: Apache Software License
Classifier: Programming Language :: Python
Classifier: Programming Language :: Python :: 2
Classifier: Programming Language :: Python :: 2.7
Classifier: Programming Language :: Python :: 3
Classifier: Programming Language :: Python :: 3.6
Classifier: Programming Language :: Python :: 3.7
Requires-Python: >2.6, !=3.0.*, !=3.1.*, !=3.2.*, !=3.3.*, !=3.4.*, !=3.5.*
